{"openapi":"3.0.2","info":{"title":"Patient Data API","description":"# REST API\n\nWork in Progress","version":"0.1.0"},"paths":{"/api/v1/patient/{patient_id}":{"get":{"tags":["patient"],"summary":"Read Records","description":"Read records","operationId":"read_records_api_v1_patient__patient_id__get","parameters":[{"required":true,"schema":{"title":"Patient Id","type":"integer"},"name":"patient_id","in":"path"}],"responses":{"200":{"description":"Successful Response","content":{"application/json":{"schema":{"$ref":"#/components/schemas/Patient"}}}},"422":{"description":"Validation Error","content":{"application/json":{"schema":{"$ref":"#/components/schemas/HTTPValidationError"}}}}}}},"/api/v1/patient/":{"get":{"tags":["patient"],"summary":"Read Records","description":"Read records","operationId":"read_records_api_v1_patient__get","parameters":[{"required":false,"schema":{"title":"Offset","type":"integer","default":0},"name":"offset","in":"query"},{"required":false,"schema":{"title":"Limit","type":"integer","default":10},"name":"limit","in":"query"},{"required":false,"schema":{"title":"Desc","type":"boolean","default":true},"name":"desc","in":"query"}],"responses":{"200":{"description":"Successful Response","content":{"application/json":{"schema":{"$ref":"#/components/schemas/PatientList"}}}},"422":{"description":"Validation Error","content":{"application/json":{"schema":{"$ref":"#/components/schemas/HTTPValidationError"}}}}}}},"/api/v1/diagnosis/":{"get":{"tags":["diagnosis"],"summary":"Read Diagnosis","description":"Read diagnosis records","operationId":"read_diagnosis_api_v1_diagnosis__get","parameters":[{"required":false,"schema":{"title":"Offset","type":"integer","default":0},"name":"offset","in":"query"},{"required":false,"schema":{"title":"Limit","type":"integer","default":10},"name":"limit","in":"query"},{"required":false,"schema":{"title":"Desc","type":"boolean","default":false},"name":"desc","in":"query"}],"responses":{"200":{"description":"Successful Response","content":{"application/json":{"schema":{"title":"Response Read Diagnosis Api V1 Diagnosis  Get","type":"array","items":{"$ref":"#/components/schemas/DiagnosisData"}}}}},"422":{"description":"Validation Error","content":{"application/json":{"schema":{"$ref":"#/components/schemas/HTTPValidationError"}}}}}}}},"components":{"schemas":{"DiagnosisData":{"title":"DiagnosisData","required":["token","diagnosis","diagnosis_en","icd11_code","icd11_title"],"type":"object","properties":{"token":{"title":"Token","type":"string"},"diagnosis":{"title":"Diagnosis","type":"string"},"diagnosis_en":{"title":"Diagnosis En","type":"string"},"icd11_code":{"title":"Icd11 Code","type":"string"},"icd11_title":{"title":"Icd11 Title","type":"string"}}},"HTTPValidationError":{"title":"HTTPValidationError","type":"object","properties":{"detail":{"title":"Detail","type":"array","items":{"$ref":"#/components/schemas/ValidationError"}}}},"Patient":{"title":"Patient","required":["patient_id","gender","age_days","weight_kg","height_cm"],"type":"object","properties":{"patient_id":{"title":"Patient Id","type":"integer"},"gender":{"title":"Gender","type":"integer"},"age_days":{"title":"Age Days","type":"integer"},"weight_kg":{"title":"Weight Kg","type":"number"},"height_cm":{"title":"Height Cm","type":"number"},"cx_prev":{"title":"Cx Prev","type":"integer"},"rachs":{"title":"Rachs","type":"integer"},"stay_days":{"title":"Stay Days","type":"integer"},"expired":{"title":"Expired","type":"integer"}}},"PatientList":{"title":"PatientList","required":["result"],"type":"object","properties":{"result":{"title":"Result","type":"array","items":{"$ref":"#/components/schemas/Patient"}}}},"ValidationError":{"title":"ValidationError","required":["loc","msg","type"],"type":"object","properties":{"loc":{"title":"Location","type":"array","items":{"anyOf":[{"type":"string"},{"type":"integer"}]}},"msg":{"title":"Message","type":"string"},"type":{"title":"Error Type","type":"string"}}}}}}